itune/__init__.py
itune/app.py
itune/choose.py
itune-0.3.0.dist-info/LICENSE
itune-0.3.0.dist-info/METADATA
itune-0.3.0.dist-info/WHEEL
itune-0.3.0.dist-info/RECORD
