Metadata-Version: 2.1
Name: itune
Version: 0.3.0
Summary: i tune your parameters so you don't have to
Author: Paul Lam
Author-email: paul@quantisan.com
Requires-Python: >=3.8,<4.0
Classifier: Programming Language :: Python :: 3
Classifier: Programming Language :: Python :: 3.8
Classifier: Programming Language :: Python :: 3.9
Classifier: Programming Language :: Python :: 3.10
Classifier: Programming Language :: Python :: 3.11
